[
  {
    "transcript": "UAV-1 move to overwatch position at latitude 44.65 longitude negative 63.58",
    "command": {
      "command_id": "a33b450e",
      "command_type": "overwatch",
      "vehicle_callsign": "UAV-1",
      "domain": "air",
      "location": {
        "lat": 44.65,
        "lon": -63.58,
        "alt_m": 100.0,
        "grid_ref": null
      },
      "parameters": {},
      "raw_transcript": "UAV-1 move to overwatch position at latitude 44.65 longitude negative 63.58",
      "risk_level": "low",
      "requires_confirmation": false,
      "timestamp": "2026-03-17T08:58:49.324603"
    },
    "timestamp": "2026-03-17T08:58:49.324834"
  },
  {
    "transcript": "UAV-1 move to overwatch position at latitude 44.65 longitude negative 63.58",
    "command": {
      "command_id": "582dae28",
      "command_type": "overwatch",
      "vehicle_callsign": "UAV-1",
      "domain": "air",
      "location": {
        "lat": 44.65,
        "lon": -63.58,
        "alt_m": 100.0,
        "grid_ref": null
      },
      "parameters": {},
      "raw_transcript": "UAV-1 move to overwatch position at latitude 44.65 longitude negative 63.58",
      "risk_level": "low",
      "requires_confirmation": false,
      "timestamp": "2026-03-17T09:00:29.877727"
    },
    "timestamp": "2026-03-17T09:00:29.877842"
  },
  {
    "transcript": "All units return to base immediately",
    "command": {
      "command_id": "eadefd33",
      "command_type": "rtb",
      "vehicle_callsign": "UAV-1",
      "domain": "air",
      "location": null,
      "parameters": {},
      "raw_transcript": "All units return to base immediately",
      "risk_level": "low",
      "requires_confirmation": false,
      "timestamp": "2026-03-17T09:01:12.032351"
    },
    "timestamp": "2026-03-17T09:01:12.032890"
  },
  {
    "transcript": "All units return to base immediately",
    "command": {
      "command_id": "7d37bd90",
      "command_type": "rtb",
      "vehicle_callsign": "UAV-2",
      "domain": "air",
      "location": null,
      "parameters": {},
      "raw_transcript": "All units return to base immediately",
      "risk_level": "low",
      "requires_confirmation": false,
      "timestamp": "2026-03-17T09:01:12.032454"
    },
    "timestamp": "2026-03-17T09:01:12.033731"
  },
  {
    "transcript": "All units return to base immediately",
    "command": {
      "command_id": "f6c22047",
      "command_type": "rtb",
      "vehicle_callsign": "UAV-3",
      "domain": "air",
      "location": null,
      "parameters": {},
      "raw_transcript": "All units return to base immediately",
      "risk_level": "low",
      "requires_confirmation": false,
      "timestamp": "2026-03-17T09:01:12.032507"
    },
    "timestamp": "2026-03-17T09:01:12.041748"
  },
  {
    "transcript": "All units return to base immediately",
    "command": {
      "command_id": "fe534939",
      "command_type": "rtb",
      "vehicle_callsign": "UGV-1",
      "domain": "ground",
      "location": null,
      "parameters": {},
      "raw_transcript": "All units return to base immediately",
      "risk_level": "low",
      "requires_confirmation": false,
      "timestamp": "2026-03-17T09:01:12.032735"
    },
    "timestamp": "2026-03-17T09:01:12.048238"
  },
  {
    "transcript": "All units return to base immediately",
    "command": {
      "command_id": "5810eed3",
      "command_type": "rtb",
      "vehicle_callsign": "UGV-2",
      "domain": "ground",
      "location": null,
      "parameters": {},
      "raw_transcript": "All units return to base immediately",
      "risk_level": "low",
      "requires_confirmation": false,
      "timestamp": "2026-03-17T09:01:12.032809"
    },
    "timestamp": "2026-03-17T09:01:12.054369"
  },
  {
    "transcript": "All units return to base immediately",
    "command": {
      "command_id": "db39e8d5",
      "command_type": "rtb",
      "vehicle_callsign": "USV-1",
      "domain": "maritime",
      "location": null,
      "parameters": {},
      "raw_transcript": "All units return to base immediately",
      "risk_level": "low",
      "requires_confirmation": false,
      "timestamp": "2026-03-17T09:01:12.032843"
    },
    "timestamp": "2026-03-17T09:01:12.060248"
  },
  {
    "transcript": "Send the vehicles, bro. Where are the vehicles at? I can't see anything.",
    "command": {
      "command_id": "5dc62903",
      "command_type": "status",
      "vehicle_callsign": "all",
      "domain": "air",
      "location": null,
      "parameters": {},
      "raw_transcript": "Send the vehicles, bro. Where are the vehicles at? I can't see anything.",
      "risk_level": "low",
      "requires_confirmation": false,
      "timestamp": "2026-03-18T06:16:24.979702"
    },
    "timestamp": "2026-03-18T06:16:24.982136"
  },
  {
    "transcript": "Move UAV 1 to Citadel Hill.",
    "command": {
      "command_id": "2ebd8479",
      "command_type": "move",
      "vehicle_callsign": "UAV-1",
      "domain": "air",
      "location": {
        "lat": 44.6478,
        "lon": -63.5802,
        "alt_m": 100.0,
        "grid_ref": null
      },
      "parameters": {},
      "raw_transcript": "Move UAV 1 to Citadel Hill.",
      "risk_level": "low",
      "requires_confirmation": false,
      "timestamp": "2026-03-18T14:29:41.793914"
    },
    "timestamp": "2026-03-18T14:29:41.794217"
  },
  {
    "transcript": "Move UAV 1 to Citadel Hill and UAV 2 should go to to go to Lower Water Street next to the Shabaktu landing.",
    "command": {
      "command_id": "24a9372f",
      "command_type": "move",
      "vehicle_callsign": "UAV-1",
      "domain": "air",
      "location": {
        "lat": 44.6478,
        "lon": -63.5802,
        "alt_m": 100.0,
        "grid_ref": null
      },
      "parameters": {},
      "raw_transcript": "Move UAV 1 to Citadel Hill and UAV 2 should go to to go to Lower Water Street next to the Shabaktu landing.",
      "risk_level": "low",
      "requires_confirmation": false,
      "timestamp": "2026-03-18T14:33:37.748048"
    },
    "timestamp": "2026-03-18T14:33:37.748486"
  },
  {
    "transcript": "Move UAV 1 to Citadel Hill and UAV 2 should go to to go to Lower Water Street next to the Shabaktu landing.",
    "command": {
      "command_id": "6d9de4b9",
      "command_type": "move",
      "vehicle_callsign": "UAV-2",
      "domain": "air",
      "location": {
        "lat": 44.643,
        "lon": -63.5672,
        "alt_m": 100.0,
        "grid_ref": null
      },
      "parameters": {},
      "raw_transcript": "Move UAV 1 to Citadel Hill and UAV 2 should go to to go to Lower Water Street next to the Shabaktu landing.",
      "risk_level": "low",
      "requires_confirmation": false,
      "timestamp": "2026-03-18T14:33:37.748332"
    },
    "timestamp": "2026-03-18T14:33:37.749850"
  },
  {
    "transcript": "Move, UAV 3, 20 centimeters to the left. Ah, sorry, 20 feet to the left. UAV 2 should start moving onto Duke Street and take a right. Keep moving.",
    "command": {
      "command_id": "6317c845",
      "command_type": "status",
      "vehicle_callsign": "UAV-2",
      "domain": "air",
      "location": null,
      "parameters": {},
      "raw_transcript": "Move, UAV 3, 20 centimeters to the left. Ah, sorry, 20 feet to the left. UAV 2 should start moving onto Duke Street and take a right. Keep moving.",
      "risk_level": "low",
      "requires_confirmation": false,
      "timestamp": "2026-03-20T00:11:33.785846"
    },
    "timestamp": "2026-03-20T00:11:33.786240"
  },
  {
    "transcript": "Move, UAV 3, 20 centimeters to the left. Ah, sorry, 20 feet to the left. UAV 2 should start moving onto Duke Street and take a right. Keep moving.",
    "command": {
      "command_id": "0abe6e95",
      "command_type": "status",
      "vehicle_callsign": "UAV-3",
      "domain": "air",
      "location": null,
      "parameters": {},
      "raw_transcript": "Move, UAV 3, 20 centimeters to the left. Ah, sorry, 20 feet to the left. UAV 2 should start moving onto Duke Street and take a right. Keep moving.",
      "risk_level": "low",
      "requires_confirmation": false,
      "timestamp": "2026-03-20T00:11:33.786075"
    },
    "timestamp": "2026-03-20T00:11:33.787410"
  },
  {
    "transcript": "UAV 2, you should start moving forward, stay on to Duke Street toward Upper Water Street and then take a right.",
    "command": {
      "command_id": "7f71a981",
      "command_type": "move",
      "vehicle_callsign": "UAV-2",
      "domain": "air",
      "location": {
        "lat": 44.646,
        "lon": -63.568,
        "alt_m": 100.0,
        "grid_ref": null
      },
      "parameters": {},
      "raw_transcript": "UAV 2, you should start moving forward, stay on to Duke Street toward Upper Water Street and then take a right.",
      "risk_level": "low",
      "requires_confirmation": false,
      "timestamp": "2026-03-20T00:12:53.854687"
    },
    "timestamp": "2026-03-20T00:12:53.855626"
  },
  {
    "transcript": "UGV 1 must engage in combat with UAV 2. It must proceed on to Argyle Street and drive into upward towards Duke Street. Take a right onto Duke Street and stop at the intersection between Duke Street and Barrington Street. Then engage combat with UAV 2 and UAV 2 is hostile. Confirm engage.",
    "command": {
      "command_id": "664ac1e6",
      "command_type": "move",
      "vehicle_callsign": "UGV-1",
      "domain": "ground",
      "location": {
        "lat": 44.649,
        "lon": -63.572,
        "alt_m": 0.0,
        "grid_ref": null
      },
      "parameters": {},
      "raw_transcript": "UGV 1 must engage in combat with UAV 2. It must proceed on to Argyle Street and drive into upward towards Duke Street. Take a right onto Duke Street and stop at the intersection between Duke Street and Barrington Street. Then engage combat with UAV 2 and UAV 2 is hostile. Confirm engage.",
      "risk_level": "low",
      "requires_confirmation": false,
      "timestamp": "2026-03-20T00:30:29.656377"
    },
    "timestamp": "2026-03-20T00:30:29.657068"
  },
  {
    "transcript": "UGV 1 must engage in combat with UAV 2. It must proceed on to Argyle Street and drive into upward towards Duke Street. Take a right onto Duke Street and stop at the intersection between Duke Street and Barrington Street. Then engage combat with UAV 2 and UAV 2 is hostile. Confirm engage.",
    "command": {
      "command_id": "57d20784",
      "command_type": "classify",
      "vehicle_callsign": "UAV-1",
      "domain": "air",
      "location": null,
      "parameters": {
        "contact_uid": "UAV-2",
        "new_affiliation": "hostile"
      },
      "raw_transcript": "UGV 1 must engage in combat with UAV 2. It must proceed on to Argyle Street and drive into upward towards Duke Street. Take a right onto Duke Street and stop at the intersection between Duke Street and Barrington Street. Then engage combat with UAV 2 and UAV 2 is hostile. Confirm engage.",
      "risk_level": "medium",
      "requires_confirmation": false,
      "timestamp": "2026-03-20T00:30:29.656751"
    },
    "timestamp": "2026-03-20T00:30:29.662202"
  },
  {
    "transcript": "UAV 1, move to the intersection between Barrington Street and Prince Street.",
    "command": {
      "command_id": "4b11ff62",
      "command_type": "move",
      "vehicle_callsign": "UAV-1",
      "domain": "air",
      "location": {
        "lat": 44.6487,
        "lon": -63.5717,
        "alt_m": 100.0,
        "grid_ref": null
      },
      "parameters": {},
      "raw_transcript": "UAV 1, move to the intersection between Barrington Street and Prince Street.",
      "risk_level": "low",
      "requires_confirmation": false,
      "timestamp": "2026-03-20T04:10:03.865480"
    },
    "timestamp": "2026-03-20T04:10:03.866228"
  },
  {
    "transcript": "Move UAV 1 to the intersection of Barrington Street and Duke Street, and wait for my second command.",
    "command": {
      "command_id": "09cc9acb",
      "command_type": "move",
      "vehicle_callsign": "UAV-1",
      "domain": "air",
      "location": {
        "lat": 44.649,
        "lon": -63.5727,
        "alt_m": 100.0,
        "grid_ref": null
      },
      "parameters": {},
      "raw_transcript": "Move UAV 1 to the intersection of Barrington Street and Duke Street, and wait for my second command.",
      "risk_level": "low",
      "requires_confirmation": false,
      "timestamp": "2026-03-20T04:18:08.639009"
    },
    "timestamp": "2026-03-20T04:18:08.639363"
  },
  {
    "transcript": "Bravo, Bravo, take off and flight to Charlie.",
    "command": {
      "command_id": "406243c1",
      "command_type": "takeoff",
      "vehicle_callsign": "Bravo",
      "domain": "air",
      "location": null,
      "parameters": {},
      "raw_transcript": "Bravo, Bravo, take off and flight to Charlie.",
      "risk_level": "low",
      "requires_confirmation": false,
      "timestamp": "2026-03-20T04:46:48.146158"
    },
    "timestamp": "2026-03-20T04:46:48.146769"
  },
  {
    "transcript": "Bravo, Bravo, take off and flight to Charlie.",
    "command": {
      "command_id": "16671b56",
      "command_type": "move",
      "vehicle_callsign": "Bravo",
      "domain": "air",
      "location": {
        "lat": 44.655,
        "lon": -63.578,
        "alt_m": 100.0,
        "grid_ref": null
      },
      "parameters": {},
      "raw_transcript": "Bravo, Bravo, take off and flight to Charlie.",
      "risk_level": "low",
      "requires_confirmation": false,
      "timestamp": "2026-03-20T04:46:48.146622"
    },
    "timestamp": "2026-03-20T04:46:48.161914"
  },
  {
    "transcript": "Bravo. Approach and rally next to Alpha and stay there.",
    "command": {
      "command_id": "20267398",
      "command_type": "move",
      "vehicle_callsign": "Bravo",
      "domain": "air",
      "location": {
        "lat": 44.6488,
        "lon": -63.5752,
        "alt_m": 100.0,
        "grid_ref": null
      },
      "parameters": {},
      "raw_transcript": "Bravo. Approach and rally next to Alpha and stay there.",
      "risk_level": "low",
      "requires_confirmation": false,
      "timestamp": "2026-03-20T04:48:00.302187"
    },
    "timestamp": "2026-03-20T04:48:00.302679"
  },
  {
    "transcript": "Bravo. Approach and rally next to Alpha and stay there.",
    "command": {
      "command_id": "17ce480a",
      "command_type": "loiter",
      "vehicle_callsign": "Bravo",
      "domain": "air",
      "location": {
        "lat": 44.6488,
        "lon": -63.5752,
        "alt_m": 100.0,
        "grid_ref": null
      },
      "parameters": {},
      "raw_transcript": "Bravo. Approach and rally next to Alpha and stay there.",
      "risk_level": "low",
      "requires_confirmation": false,
      "timestamp": "2026-03-20T04:48:00.302562"
    },
    "timestamp": "2026-03-20T04:48:00.312466"
  },
  {
    "transcript": "Engage combat with Alpha Bravo engage combat with Alpha Alpha is hostile",
    "command": {
      "command_id": "8119238d",
      "command_type": "engage",
      "vehicle_callsign": "Bravo",
      "domain": "air",
      "location": null,
      "parameters": {
        "target_uid": "Alpha"
      },
      "raw_transcript": "Engage combat with Alpha Bravo engage combat with Alpha Alpha is hostile",
      "risk_level": "critical",
      "requires_confirmation": true,
      "timestamp": "2026-03-20T04:48:59.695072"
    },
    "timestamp": "2026-03-20T04:48:59.697176"
  },
  {
    "transcript": "Engage combat with Alpha Bravo engage combat with Alpha Alpha is hostile",
    "command": {
      "command_id": "af1259ae",
      "command_type": "classify",
      "vehicle_callsign": "Alpha",
      "domain": "air",
      "location": null,
      "parameters": {
        "contact_uid": "Alpha",
        "new_affiliation": "hostile"
      },
      "raw_transcript": "Engage combat with Alpha Bravo engage combat with Alpha Alpha is hostile",
      "risk_level": "medium",
      "requires_confirmation": false,
      "timestamp": "2026-03-20T04:48:59.697062"
    },
    "timestamp": "2026-03-20T04:48:59.705882"
  },
  {
    "transcript": "Alpha, take off to 20 meters.",
    "command": {
      "command_id": "a448a630",
      "command_type": "takeoff",
      "vehicle_callsign": "Alpha",
      "domain": "air",
      "location": null,
      "parameters": {
        "alt_m": 20
      },
      "raw_transcript": "Alpha, take off to 20 meters.",
      "risk_level": "low",
      "requires_confirmation": false,
      "timestamp": "2026-03-20T08:24:45.103475"
    },
    "timestamp": "2026-03-20T08:24:45.103718"
  },
  {
    "transcript": "Alpha, proceed forward and make a smooth landing onto the runway.",
    "command": {
      "command_id": "fe0240a4",
      "command_type": "land",
      "vehicle_callsign": "Alpha",
      "domain": "air",
      "location": null,
      "parameters": {},
      "raw_transcript": "Alpha, proceed forward and make a smooth landing onto the runway.",
      "risk_level": "low",
      "requires_confirmation": false,
      "timestamp": "2026-03-20T08:27:04.842861"
    },
    "timestamp": "2026-03-20T08:27:04.843152"
  },
  {
    "transcript": "Alpha, takeoff to 20 meters and move forward for 10 seconds.",
    "command": {
      "command_id": "49c8f77b",
      "command_type": "takeoff",
      "vehicle_callsign": "Alpha",
      "domain": "air",
      "location": null,
      "parameters": {
        "alt_m": 20
      },
      "raw_transcript": "Alpha, takeoff to 20 meters and move forward for 10 seconds.",
      "risk_level": "low",
      "requires_confirmation": false,
      "timestamp": "2026-03-20T08:28:42.912016"
    },
    "timestamp": "2026-03-20T08:28:42.912513"
  },
  {
    "transcript": "Take off to 10 meters",
    "command": {
      "command_id": "627d68ed",
      "command_type": "takeoff",
      "vehicle_callsign": "Alpha",
      "domain": "air",
      "location": null,
      "parameters": {
        "alt_m": 10
      },
      "raw_transcript": "Take off to 10 meters",
      "risk_level": "low",
      "requires_confirmation": false,
      "timestamp": "2026-03-21T15:56:51.736112"
    },
    "timestamp": "2026-03-21T15:56:51.736291"
  },
  {
    "transcript": "Fly north 50 meters",
    "command": {
      "command_id": "cc6a93b4",
      "command_type": "move",
      "vehicle_callsign": "Alpha",
      "domain": "air",
      "location": {
        "lat": 0.00044991169133322515,
        "lon": 0.0,
        "alt_m": 0.0,
        "grid_ref": null
      },
      "parameters": {
        "original_tool": "move_relative"
      },
      "raw_transcript": "Fly north 50 meters",
      "risk_level": "low",
      "requires_confirmation": false,
      "timestamp": "2026-03-21T15:56:52.835570"
    },
    "timestamp": "2026-03-21T15:56:52.835692"
  },
  {
    "transcript": "Fly to the northwest watch tower",
    "command": {
      "command_id": "8dafe093",
      "command_type": "move",
      "vehicle_callsign": "Alpha",
      "domain": "air",
      "location": {
        "lat": 32.9903329,
        "lon": -106.9756115,
        "alt_m": 100.0,
        "grid_ref": null
      },
      "parameters": {},
      "raw_transcript": "Fly to the northwest watch tower",
      "risk_level": "low",
      "requires_confirmation": false,
      "timestamp": "2026-03-21T15:56:54.100828"
    },
    "timestamp": "2026-03-21T15:56:54.100913"
  },
  {
    "transcript": "Descend to 5 meters",
    "command": {
      "command_id": "2d972f66",
      "command_type": "move",
      "vehicle_callsign": "Alpha",
      "domain": "air",
      "location": {
        "lat": 0.0,
        "lon": 0.0,
        "alt_m": 5.0,
        "grid_ref": null
      },
      "parameters": {
        "original_tool": "set_altitude"
      },
      "raw_transcript": "Descend to 5 meters",
      "risk_level": "low",
      "requires_confirmation": false,
      "timestamp": "2026-03-21T15:56:54.935938"
    },
    "timestamp": "2026-03-21T15:56:54.936014"
  },
  {
    "transcript": "Fly east to the command building",
    "command": {
      "command_id": "d51202fc",
      "command_type": "move",
      "vehicle_callsign": "Alpha",
      "domain": "air",
      "location": {
        "lat": 32.990126,
        "lon": -106.9747318,
        "alt_m": 100.0,
        "grid_ref": null
      },
      "parameters": {},
      "raw_transcript": "Fly east to the command building",
      "risk_level": "low",
      "requires_confirmation": false,
      "timestamp": "2026-03-21T15:56:55.921204"
    },
    "timestamp": "2026-03-21T15:56:55.921295"
  },
  {
    "transcript": "Climb to 12 meters and hover over the rooftop",
    "command": {
      "command_id": "d786e4b2",
      "command_type": "move",
      "vehicle_callsign": "Alpha",
      "domain": "air",
      "location": {
        "lat": 0.0,
        "lon": 0.0,
        "alt_m": 12.0,
        "grid_ref": null
      },
      "parameters": {
        "original_tool": "set_altitude"
      },
      "raw_transcript": "Climb to 12 meters and hover over the rooftop",
      "risk_level": "low",
      "requires_confirmation": false,
      "timestamp": "2026-03-21T15:56:57.403061"
    },
    "timestamp": "2026-03-21T15:56:57.403389"
  },
  {
    "transcript": "Climb to 12 meters and hover over the rooftop",
    "command": {
      "command_id": "1d3d0022",
      "command_type": "loiter",
      "vehicle_callsign": "Alpha",
      "domain": "air",
      "location": {
        "lat": 32.990126,
        "lon": -106.9747318,
        "alt_m": 12.0,
        "grid_ref": null
      },
      "parameters": {},
      "raw_transcript": "Climb to 12 meters and hover over the rooftop",
      "risk_level": "low",
      "requires_confirmation": false,
      "timestamp": "2026-03-21T15:56:57.403312"
    },
    "timestamp": "2026-03-21T15:56:57.405640"
  },
  {
    "transcript": "Fly to the fuel depot",
    "command": {
      "command_id": "b3a89590",
      "command_type": "move",
      "vehicle_callsign": "Alpha",
      "domain": "air",
      "location": {
        "lat": 32.9897121,
        "lon": -106.9752897,
        "alt_m": 100.0,
        "grid_ref": null
      },
      "parameters": {},
      "raw_transcript": "Fly to the fuel depot",
      "risk_level": "low",
      "requires_confirmation": false,
      "timestamp": "2026-03-21T15:56:58.506036"
    },
    "timestamp": "2026-03-21T15:56:58.506223"
  },
  {
    "transcript": "Report current position and altitude",
    "command": {
      "command_id": "e5121f15",
      "command_type": "status",
      "vehicle_callsign": "all",
      "domain": "air",
      "location": null,
      "parameters": {},
      "raw_transcript": "Report current position and altitude",
      "risk_level": "low",
      "requires_confirmation": false,
      "timestamp": "2026-03-21T15:56:59.325535"
    },
    "timestamp": "2026-03-21T15:56:59.325617"
  },
  {
    "transcript": "Fly south to the shipping containers",
    "command": {
      "command_id": "5855b1dd",
      "command_type": "move",
      "vehicle_callsign": "Alpha",
      "domain": "air",
      "location": {
        "lat": 32.9898515,
        "lon": -106.9749839,
        "alt_m": 100.0,
        "grid_ref": null
      },
      "parameters": {},
      "raw_transcript": "Fly south to the shipping containers",
      "risk_level": "low",
      "requires_confirmation": false,
      "timestamp": "2026-03-21T15:57:00.366819"
    },
    "timestamp": "2026-03-21T15:57:00.367034"
  },
  {
    "transcript": "Drop to 3 meters and enter the motor pool",
    "command": {
      "command_id": "f37c523b",
      "command_type": "move",
      "vehicle_callsign": "Alpha",
      "domain": "air",
      "location": {
        "lat": 0.0,
        "lon": 0.0,
        "alt_m": 3.0,
        "grid_ref": null
      },
      "parameters": {
        "original_tool": "set_altitude"
      },
      "raw_transcript": "Drop to 3 meters and enter the motor pool",
      "risk_level": "low",
      "requires_confirmation": false,
      "timestamp": "2026-03-21T15:57:01.767422"
    },
    "timestamp": "2026-03-21T15:57:01.767713"
  },
  {
    "transcript": "Drop to 3 meters and enter the motor pool",
    "command": {
      "command_id": "bd80d40d",
      "command_type": "move",
      "vehicle_callsign": "Alpha",
      "domain": "air",
      "location": {
        "lat": 32.98982,
        "lon": -106.9745923,
        "alt_m": 100.0,
        "grid_ref": null
      },
      "parameters": {},
      "raw_transcript": "Drop to 3 meters and enter the motor pool",
      "risk_level": "low",
      "requires_confirmation": false,
      "timestamp": "2026-03-21T15:57:01.767644"
    },
    "timestamp": "2026-03-21T15:57:01.773036"
  },
  {
    "transcript": "Go to the northeast tower at 15 meters altitude",
    "command": {
      "command_id": "b5989c41",
      "command_type": "move",
      "vehicle_callsign": "Alpha",
      "domain": "air",
      "location": {
        "lat": 32.9903329,
        "lon": -106.9743885,
        "alt_m": 15.0,
        "grid_ref": null
      },
      "parameters": {},
      "raw_transcript": "Go to the northeast tower at 15 meters altitude",
      "risk_level": "low",
      "requires_confirmation": false,
      "timestamp": "2026-03-21T15:57:03.188648"
    },
    "timestamp": "2026-03-21T15:57:03.188773"
  },
  {
    "transcript": "Head back to the landing pad",
    "command": {
      "command_id": "904d7a00",
      "command_type": "rtb",
      "vehicle_callsign": "Alpha",
      "domain": "air",
      "location": null,
      "parameters": {},
      "raw_transcript": "Head back to the landing pad",
      "risk_level": "low",
      "requires_confirmation": false,
      "timestamp": "2026-03-21T15:57:04.429442"
    },
    "timestamp": "2026-03-21T15:57:04.429521"
  },
  {
    "transcript": "Land",
    "command": {
      "command_id": "30a1b6bf",
      "command_type": "land",
      "vehicle_callsign": "Alpha",
      "domain": "air",
      "location": null,
      "parameters": {},
      "raw_transcript": "Land",
      "risk_level": "low",
      "requires_confirmation": false,
      "timestamp": "2026-03-21T15:57:05.234698"
    },
    "timestamp": "2026-03-21T15:57:05.234780"
  },
  {
    "transcript": "Turn off the engines and self-destruct",
    "command": {
      "command_id": "10c17abb",
      "command_type": "land",
      "vehicle_callsign": "Alpha",
      "domain": "air",
      "location": null,
      "parameters": {},
      "raw_transcript": "Turn off the engines and self-destruct",
      "risk_level": "low",
      "requires_confirmation": false,
      "timestamp": "2026-03-21T15:57:07.067755"
    },
    "timestamp": "2026-03-21T15:57:07.067818"
  }
]